fx2obp/__init__.py
fx2obp/convert.py
fx2obp/fetch_currencies.py
fx2obp-0.2.dist-info/METADATA
fx2obp-0.2.dist-info/WHEEL
fx2obp-0.2.dist-info/top_level.txt
fx2obp-0.2.dist-info/RECORD
