Metadata-Version: 2.1
Name: fx2obp
Version: 0.2
Summary: Convert exchange rates to OBP format, and optionally post to an OBP instance
Home-page: https://github.com/chrisjsimpson/fx2obp
Author: Chris Simpson
Author-email: chris15leicester@gmail.com
License: UNKNOWN
Platform: UNKNOWN
Classifier: Programming Language :: Python :: 3
Classifier: License :: OSI Approved :: GNU Affero General Public License v3
Classifier: Operating System :: OS Independent
Requires-Dist: bs4
Requires-Dist: requests
